pulser_myqlm/__init__.py
pulser_myqlm/_version.py
pulser_myqlm/connection.py
pulser_myqlm/constants.py
pulser_myqlm/fresnel_qpu.py
pulser_myqlm/ising_aqpu.py
pulser_myqlm/myqlmtools.py
pulser_myqlm/pulserAQPU.py
pulser_myqlm/temp_device.json
pulser_myqlm/helpers/__init__.py
pulser_myqlm/helpers/deserialize_other.py
pulser_myqlm/helpers/qlm_connection.py
pulser_myqlm/helpers/requests.py
pulser_myqlm/helpers/simulate_seq.py
pulser_myqlm-0.8.3.dist-info/licenses/LICENSE
tests/__init__.py
tests/conftest.py
tests/test_compatiblity.py
tests/test_connection.py
tests/test_fresnel_qpu.py
tests/test_ising_aqpu.py
tests/test_myqlm_tools.py
pulser_myqlm-0.8.3.dist-info/METADATA
pulser_myqlm-0.8.3.dist-info/WHEEL
pulser_myqlm-0.8.3.dist-info/top_level.txt
pulser_myqlm-0.8.3.dist-info/RECORD
