Metadata-Version: 2.4
Name: pulser-myqlm
Version: 0.8.3
Summary: An extension to interface MyQLM with Pulser.
Author: Pasqal Quantum Solutions / Pulser Development Team
License: Apache 2.0
Requires-Python: >=3.9.0
License-File: LICENSE
Requires-Dist: numpy
Requires-Dist: scipy
Requires-Dist: pulser-core>=1.4.0
Requires-Dist: pulser-simulation>=1.4.0
Requires-Dist: myqlm!=1.10.4,>=1.9.0
Requires-Dist: requests
Requires-Dist: backoff~=2.2
Provides-Extra: dev
Requires-Dist: pytest-cov; extra == "dev"
Requires-Dist: flake8-docstrings; extra == "dev"
Requires-Dist: black[jupyter]; extra == "dev"
Requires-Dist: isort; extra == "dev"
Requires-Dist: mypy==0.991; extra == "dev"
Requires-Dist: types-requests; extra == "dev"
Requires-Dist: notebook; extra == "dev"
Requires-Dist: python-igraph; extra == "dev"
Provides-Extra: test-dev
Requires-Dist: pytest-cov; extra == "test-dev"
Dynamic: author
Dynamic: description
Dynamic: description-content-type
Dynamic: license
Dynamic: license-file
Dynamic: provides-extra
Dynamic: requires-dist
Dynamic: requires-python
Dynamic: summary
